docstring_auditor/__init__.py
docstring_auditor/main.py
docstring_auditor-0.1.15.dist-info/METADATA
docstring_auditor-0.1.15.dist-info/WHEEL
docstring_auditor-0.1.15.dist-info/licenses/LICENSE
docstring_auditor-0.1.15.dist-info/RECORD
