Metadata-Version: 2.1
Name: docstring-auditor
Version: 0.1.15
Summary: A tool to analyze Python functions' docstrings and provide critiques and suggestions for improvement
Author-email: Rob Luke <rob.luke@ae.studio>
License-File: LICENSE
Keywords: auditor,docstring,gpt,openai
Classifier: Development Status :: 3 - Alpha
Classifier: Intended Audience :: Developers
Classifier: License :: OSI Approved :: Apache Software License
Classifier: Programming Language :: Python
Classifier: Programming Language :: Python :: 3
Classifier: Programming Language :: Python :: 3.8
Classifier: Programming Language :: Python :: 3.9
Classifier: Programming Language :: Python :: 3.10
Classifier: Programming Language :: Python :: 3.11
